eac_info/__init__.py
eac_info/exceptions.py
eac_info/get_eac_info.py
eac_info/model.py
rust_eac_information-0.2.0.dist-info/WHEEL
rust_eac_information-0.2.0.dist-info/METADATA
rust_eac_information-0.2.0.dist-info/RECORD
