Metadata-Version: 2.1
Name: rust-eac-information
Version: 0.2.0
Summary: Get infromation about eac banned players in rust
Home-page: https://github.com/MaHryCT3/rust-eac-infromation
License: MIT
Keywords: eac,rust,python
Author: MaHryCT3
Author-email: mahryct123@gmail.com
Requires-Python: >=3.10,<4.0
Classifier: License :: OSI Approved :: MIT License
Classifier: Programming Language :: Python :: 3
Classifier: Programming Language :: Python :: 3.10
Requires-Dist: aiohttp (>=3.8.1,<4.0.0)
Requires-Dist: beautifulsoup4 (>=4.11.1,<5.0.0)
Requires-Dist: lxml (>=4.9.1,<5.0.0)
Project-URL: Repository, https://github.com/MaHryCT3/rust-eac-infromation
